occ.py
opencontest_cli-2.8.0.dist-info/LICENSE
opencontest_cli-2.8.0.dist-info/METADATA
opencontest_cli-2.8.0.dist-info/WHEEL
opencontest_cli-2.8.0.dist-info/entry_points.txt
opencontest_cli-2.8.0.dist-info/top_level.txt
opencontest_cli-2.8.0.dist-info/RECORD
