Metadata-Version: 2.1
Name: opencontest-cli
Version: 2.8.0
Summary: A very simple OpenContest command line client written in Python
Home-page: https://github.com/LadueCS/OpenContest-CLI
Author: Anthony Wang
Author-email: ta180m@pm.me
License: UNKNOWN
Project-URL: Bug Tracker, https://github.com/LadueCS/OpenContest-CLI/issues
Platform: UNKNOWN
Classifier: Programming Language :: Python :: 3
Classifier: License :: OSI Approved :: GNU General Public License v3 (GPLv3)
Classifier: Operating System :: OS Independent
Classifier: Environment :: Console
Classifier: Intended Audience :: End Users/Desktop
License-File: LICENSE
Requires-Dist: requests
